monitoring/__init__.py
monitoring/dashboard.py
monitoring/models.py
monitoring/alarmdefs/__init__.py
monitoring/alarmdefs/constants.py
monitoring/alarmdefs/forms.py
monitoring/alarmdefs/panel.py
monitoring/alarmdefs/tables.py
monitoring/alarmdefs/tests.py
monitoring/alarmdefs/urls.py
monitoring/alarmdefs/views.py
monitoring/alarmdefs/workflows.py
monitoring/alarmdefs/templates/alarmdefs/_create_ad_details_help.html
monitoring/alarmdefs/templates/alarmdefs/_create_ad_expression_help.html
monitoring/alarmdefs/templates/alarmdefs/_create_ad_notification_help.html
monitoring/alarmdefs/templates/alarmdefs/_detail.html
monitoring/alarmdefs/templates/alarmdefs/_edit.html
monitoring/alarmdefs/templates/alarmdefs/alarm.html
monitoring/alarmdefs/templates/alarmdefs/detail.html
monitoring/alarmdefs/templates/alarmdefs/edit.html
monitoring/alarmdefs/templates/alarmdefs/expression_field.html
monitoring/alarmdefs/templates/alarmdefs/match_by_field.html
monitoring/alarmdefs/templates/alarmdefs/notification_field.html
monitoring/alarmdefs/templates/alarmdefs/workflow_step.html
monitoring/alarms/__init__.py
monitoring/alarms/constants.py
monitoring/alarms/forms.py
monitoring/alarms/panel.py
monitoring/alarms/tables.py
monitoring/alarms/tests.py
monitoring/alarms/urls.py
monitoring/alarms/views.py
monitoring/alarms/templates/alarms/_filter.html
monitoring/alarms/templates/alarms/alarm.html
monitoring/alarms/templates/alarms/alarm_history.html
monitoring/alarms/templates/alarms/alarm_meter.html
monitoring/alarms/templates/alarms/filter.html
monitoring/api/__init__.py
monitoring/api/client.py
monitoring/api/monitor.py
monitoring/conf/monitoring_policy.yaml
monitoring/config/__init__.py
monitoring/config/local_settings.py
monitoring/disabled/_70_remove_monasca_notification_panel.py
monitoring/disabled/__init__.py
monitoring/enabled/_50_admin_add_monitoring_panel.py
monitoring/enabled/__init__.py
monitoring/locale/de/LC_MESSAGES/django.po
monitoring/locale/de/LC_MESSAGES/djangojs.po
monasca_ui-9.0.0.dist-info/AUTHORS
monasca_ui-9.0.0.dist-info/LICENSE
monasca_ui-9.0.0.dist-info/METADATA
monasca_ui-9.0.0.dist-info/WHEEL
monasca_ui-9.0.0.dist-info/pbr.json
monasca_ui-9.0.0.dist-info/top_level.txt
monasca_ui-9.0.0.dist-info/RECORD
